flow/__init__.py
flow/factory.py
flow/flow_builder.py
flow/materializer.py
flow/middleware.py
flow/shell.py
flow/core/__init__.py
flow/core/ports.py
flow/core/strategies.py
flow/core/types.py
flow/nodes/__init__.py
flow/nodes/base.py
flow/nodes/source.py
flow/nodes/unified.py
flokkit_flow-0.2.1.dist-info/METADATA
flokkit_flow-0.2.1.dist-info/WHEEL
flokkit_flow-0.2.1.dist-info/top_level.txt
flokkit_flow-0.2.1.dist-info/RECORD
