Metadata-Version: 2.4
Name: flokkit-flow
Version: 0.2.1
Summary: A type-safe, async-first flow-based programming framework for Python
Author-email: Your Name <your.email@example.com>
License: MIT
Project-URL: Homepage, https://gitlab.com/flokkit/flow
Project-URL: Documentation, https://flokkit.gitlab.io/flow/
Project-URL: Repository, https://gitlab.com/flokkit/flow
Project-URL: Issues, https://gitlab.com/flokkit/flow/-/issues
Keywords: flow-based-programming,fbp,dataflow,async,pipeline
Classifier: Development Status :: 4 - Beta
Classifier: Intended Audience :: Developers
Classifier: License :: OSI Approved :: MIT License
Classifier: Programming Language :: Python :: 3
Classifier: Programming Language :: Python :: 3.8
Classifier: Programming Language :: Python :: 3.9
Classifier: Programming Language :: Python :: 3.10
Classifier: Programming Language :: Python :: 3.11
Classifier: Programming Language :: Python :: 3.12
Classifier: Topic :: Software Development :: Libraries :: Python Modules
Classifier: Typing :: Typed
Requires-Python: >=3.8
Provides-Extra: test
Requires-Dist: pytest>=7.0.0; extra == "test"
Requires-Dist: pytest-asyncio>=0.21.0; extra == "test"
Requires-Dist: pytest-cov>=4.0.0; extra == "test"
Requires-Dist: coverage[toml]>=7.0; extra == "test"
Provides-Extra: dev
Requires-Dist: pytest>=7.0.0; extra == "dev"
Requires-Dist: pytest-asyncio>=0.21.0; extra == "dev"
Requires-Dist: basedpyright>=1.10.0; extra == "dev"
Requires-Dist: ruff>=0.1.0; extra == "dev"
Provides-Extra: docs
Requires-Dist: sphinx>=7.0; extra == "docs"
Requires-Dist: sphinx-rtd-theme>=2.0; extra == "docs"
Requires-Dist: sphinx-autodoc-typehints>=2.0; extra == "docs"
Requires-Dist: sphinx-copybutton>=0.5; extra == "docs"
Requires-Dist: myst-parser>=2.0; extra == "docs"
Requires-Dist: sphinx-autobuild>=2024.0; extra == "docs"
Requires-Dist: linkify-it-py>=2.0; extra == "docs"
